data/cells.csv
data/genes.csv
phn/__init__.py
phn/_modidx.py
phn/meta.py
phn/read.py
phn/types.py
phn/csvs/cells.csv
phn/csvs/genes.csv
phn-0.0.13.dist-info/LICENSE
phn-0.0.13.dist-info/METADATA
phn-0.0.13.dist-info/WHEEL
phn-0.0.13.dist-info/entry_points.txt
phn-0.0.13.dist-info/top_level.txt
phn-0.0.13.dist-info/RECORD
