Metadata-Version: 2.1
Name: phn
Version: 0.0.13
Summary: phn
Home-page: https://github.com/dsm-72/phn
Author: dsm-72
Author-email: sumner.magruder@yale.edu
License: Apache Software License 2.0
Keywords: phn phenotype cell biology
Classifier: Development Status :: 4 - Beta
Classifier: Intended Audience :: Developers
Classifier: Natural Language :: English
Classifier: Programming Language :: Python :: 3.11
Classifier: License :: OSI Approved :: Apache Software License
Requires-Python: >=3.11
License-File: LICENSE
Requires-Dist: atyp
Requires-Dist: nchr
Requires-Dist: nlit
Requires-Dist: chck
Requires-Dist: ensc
Requires-Dist: pstr
Requires-Dist: ston
Requires-Dist: pandas
Requires-Dist: importlib-resources
Provides-Extra: dev
Requires-Dist: numpy >=1.22 ; extra == 'dev'
Requires-Dist: torch ; extra == 'dev'
Requires-Dist: anndata ; extra == 'dev'
Requires-Dist: scipy ; extra == 'dev'
